phys/__init__.py
phys/bodies.py
phys/draw.py
phys/examples/__init__.py
phys/examples/balls.py
phys/examples/gas.py
phys/examples/shapes.py
pyxel_physics-0.1.0.dist-info/LICENSE
pyxel_physics-0.1.0.dist-info/WHEEL
pyxel_physics-0.1.0.dist-info/METADATA
pyxel_physics-0.1.0.dist-info/RECORD
