Metadata-Version: 2.1
Name: pyxel-physics
Version: 0.1.0
Summary: Physics module that merges Pymunk with Pyxel.
Home-page: https://github.com/fisjogos-fga/pyxel-physics
License: UNKNOWN
Author: Fábio Macêdo Mendes
Author-email: fabiomacedomendes@gmail.com
Classifier: License :: OSI Approved :: MIT License
Requires-Dist: pyxel >= 1.4.0
